perplexity/__init__.py
perplexity/client.py
perplexity/driver.py
perplexity/emailnator.py
perplexity/labs.py
perplexity_api-1.0.5.dist-info/METADATA
perplexity_api-1.0.5.dist-info/WHEEL
perplexity_api-1.0.5.dist-info/top_level.txt
perplexity_api-1.0.5.dist-info/RECORD
