Metadata-Version: 2.2
Name: perplexity-api
Version: 1.0.5
Summary: Unofficial API Wrapper for Perplexity.ai + Account Generator with Web Interface
Home-page: https://github.com/helallao/perplexity-ai
Author: helallao
Author-email: aliyasar8585@gmail.com
License: MIT License
Project-URL: Source Code, https://github.com/helallao/perplexity-ai
Requires-Dist: curl_cffi
Dynamic: author
Dynamic: author-email
Dynamic: description
Dynamic: description-content-type
Dynamic: home-page
Dynamic: license
Dynamic: project-url
Dynamic: requires-dist
Dynamic: summary
